{
  "project_info": {
    "project_number": "920463898881",
    "firebase_url": "https://cs4048-lab2.firebaseio.com",
    "project_id": "cs4048-lab2",
    "storage_bucket": "cs4048-lab2.appspot.com"
  },
  "client": [
    {
      "client_info": {
        "mobilesdk_app_id": "1:920463898881:android:9c698abf90bd04c35fc300",
        "android_client_info": {
          "package_name": "com.example.assignment_2"
        }
      },
      "oauth_client": [
        {
          "client_id": "920463898881-ggmh56e1sb7d6an17sjhcfu8liq4vp3h.apps.googleusercontent.com",
          "client_type": 1,
          "android_info": {
            "package_name": "com.example.assignment_2",
            "certificate_hash": "f6057b40a0998fc83a68b4031c10a30ef006d2b4"
          }
        },
        {
          "client_id": "920463898881-2iea1cld843l5td5o5am7t7fids55lof.apps.googleusercontent.com",
          "client_type": 3
        }
      ],
      "api_key": [
        {
          "current_key": "AIzaSyDH4Z2sgBuje1tWIHCvRPmDXkOahehylFw"
        }
      ],
      "services": {
        "appinvite_service": {
          "other_platform_oauth_client": [
            {
              "client_id": "920463898881-2iea1cld843l5td5o5am7t7fids55lof.apps.googleusercontent.com",
              "client_type": 3
            }
          ]
        }
      }
    }
  ],
  "configuration_version": "1"
}